{"projects":[{"projectID":1,"projectName":"Bug Tracking System","dateOfStart":"2023-05-07","teamSize":6,"active":true,"status":"In Force","clientLocationID":1,"clientLocation":{"clientLocationID":1,"clientLocationName":"Boston"}},{"projectID":2,"projectName":"COVID-19 Tracker","dateOfStart":"2020-03-15","teamSize":17,"active":true,"status":"Support","clientLocationID":2,"clientLocation":{"clientLocationID":2,"clientLocationName":"London"}},{"projectID":"3","projectName":"aaa","dateOfStart":"2022-01-18","teamSize":"3","active":true,"status":"In Force","clientLocationID":"2","clientLocation":{"clientLocationID":0,"clientLocationName":null}},{"projectID":"4","projectName":"bbb","dateOfStart":"2022-01-27","teamSize":"56","active":true,"status":"Support","clientLocationID":"2","clientLocation":{"clientLocationID":0,"clientLocationName":null}},{"projectID":"5","projectName":"dfgdfg","dateOfStart":"2022-01-09","teamSize":"34","active":true,"status":"In Force","clientLocationID":"3","clientLocation":{"clientLocationID":3,"clientLocationName":"New Jersy"}},{"projectID":"6","projectName":"sdfggdg","dateOfStart":"2022-01-18","teamSize":"33","active":false,"status":"Support","clientLocationID":"1","clientLocation":{"clientLocationID":1,"clientLocationName":"Boston"}}],"roles":[{"id":1,"roleName":"Admin"},{"id":2,"roleName":"Employee"}],"users":[{"id":1,"UserName":"admin","Email":"admin@gmail.com","Password":"Admin123#","Role":"Admin"}],"clientLocations":[{"clientLocationID":1,"clientLocationName":"Boston"},{"clientLocationID":2,"clientLocationName":"London"},{"clientLocationID":3,"clientLocationName":"New Jersy"}]}